{"cameraMode":{"drawMode":0,"name":"Shaded","section":"Shading Mode"},"sceneLighting":false,"audioPlay":false,"sceneViewState":{"m_AlwaysRefresh":false,"showFog":true,"showSkybox":false,"showFlares":true,"showImageEffects":true,"showParticleSystems":true,"showVisualEffectGraphs":true,"m_FxEnabled":true},"in2DMode":false,"pivot":{"x":0.0,"y":0.8889560699462891,"z":0.010344117879867554},"rotation":{"x":-0.059036653488874438,"y":0.7927621603012085,"z":-0.0777880921959877,"w":-0.6016602516174316},"size":1.050541639328003,"orthographic":false}